{
  "schemaVersion": "1.2.0",
  "data": [
    {
      "built": true,
      "tested": null,
      "toolchain": "leanprover/lean4:v4.17.0-rc1",
      "requiredUpdate": false,
      "archiveSize": 717501,
      "archiveHash": null,
      "runAt": "2025-02-13T14:13:46Z",
      "url": "https://github.com/leanprover/reservoir/actions/runs/13309439883/job/37168269426#step:4:1",
      "revision": "49dd69c9e7c50b34bce5c00083ae2255041b983e"
    },
    {
      "built": true,
      "tested": null,
      "toolchain": "leanprover/lean4:v4.17.0-rc1",
      "requiredUpdate": false,
      "archiveSize": 717497,
      "archiveHash": null,
      "runAt": "2025-02-12T14:17:53Z",
      "url": "https://github.com/leanprover/reservoir/actions/runs/13287148260/job/37098729739#step:4:1",
      "revision": "49dd69c9e7c50b34bce5c00083ae2255041b983e"
    },
    {
      "built": true,
      "tested": null,
      "toolchain": "leanprover/lean4:v4.17.0-rc1",
      "requiredUpdate": false,
      "archiveSize": 776449,
      "archiveHash": null,
      "runAt": "2025-02-09T14:12:13Z",
      "url": "https://github.com/leanprover/reservoir/actions/runs/13226419003/job/36917916254#step:4:1",
      "revision": "a9898d716323068942c0ffa9b45a2280c6135b6f"
    },
    {
      "built": true,
      "tested": null,
      "toolchain": "leanprover/lean4:v4.16.0",
      "requiredUpdate": false,
      "archiveSize": 776393,
      "archiveHash": null,
      "runAt": "2025-02-08T14:14:01Z",
      "url": "https://github.com/leanprover/reservoir/actions/runs/13216331473/job/36896077134#step:4:1",
      "revision": "a9898d716323068942c0ffa9b45a2280c6135b6f"
    },
    {
      "built": true,
      "tested": null,
      "toolchain": "leanprover/lean4:v4.16.0-rc2",
      "requiredUpdate": false,
      "archiveSize": 775751,
      "archiveHash": null,
      "runAt": "2025-02-05T14:16:30Z",
      "url": "https://github.com/leanprover/reservoir/actions/runs/13159093594/job/36723279085#step:4:1",
      "revision": "a9898d716323068942c0ffa9b45a2280c6135b6f"
    },
    {
      "built": true,
      "tested": null,
      "toolchain": "leanprover/lean4:v4.16.0-rc2",
      "requiredUpdate": false,
      "archiveSize": 972833,
      "archiveHash": null,
      "runAt": "2025-02-02T14:12:22Z",
      "url": "https://github.com/leanprover/reservoir/actions/runs/13099485624/job/36546005107#step:4:1",
      "revision": "fdf2f75e96fa727674e1bf701e637c12cf7db593"
    },
    {
      "built": true,
      "tested": null,
      "toolchain": "leanprover/lean4:v4.15.0",
      "requiredUpdate": false,
      "archiveSize": 973600,
      "archiveHash": null,
      "runAt": "2025-02-01T14:14:42Z",
      "url": "https://github.com/leanprover/reservoir/actions/runs/13089329110/job/36524222064#step:4:1",
      "revision": "fdf2f75e96fa727674e1bf701e637c12cf7db593"
    },
    {
      "built": false,
      "tested": null,
      "toolchain": "leanprover/lean4:v4.15.0",
      "requiredUpdate": false,
      "archiveSize": null,
      "archiveHash": null,
      "runAt": "2025-01-28T14:14:45Z",
      "url": "https://github.com/leanprover/reservoir/actions/runs/13012188162/job/36292552079#step:4:1",
      "revision": "238fa11ab679dfc897144496396e0fe180466dbd"
    },
    {
      "built": true,
      "tested": null,
      "toolchain": "leanprover/lean4:v4.16.0-rc2",
      "requiredUpdate": false,
      "archiveSize": 1072812,
      "archiveHash": null,
      "runAt": "2025-01-27T14:16:20Z",
      "url": "https://github.com/leanprover/reservoir/actions/runs/12990720349/job/36226785100#step:4:1",
      "revision": "238fa11ab679dfc897144496396e0fe180466dbd"
    },
    {
      "built": true,
      "tested": null,
      "toolchain": "leanprover/lean4:v4.16.0-rc2",
      "requiredUpdate": false,
      "archiveSize": 1153277,
      "archiveHash": null,
      "runAt": "2025-01-23T14:13:12Z",
      "url": "https://github.com/leanprover/reservoir/actions/runs/12930848792/job/36063541552#step:4:1",
      "revision": "c24d2320ac26e0047d578a79c2ba7da1d9e2742e"
    },
    {
      "built": true,
      "tested": null,
      "toolchain": "leanprover/lean4:v4.16.0-rc2",
      "requiredUpdate": false,
      "archiveSize": 1180740,
      "archiveHash": null,
      "runAt": "2025-01-22T14:16:28Z",
      "url": "https://github.com/leanprover/reservoir/actions/runs/12909882023/job/35998836751#step:4:1",
      "revision": "f20d1039e650b3eb2490d02356c1fb99b261693d"
    },
    {
      "built": true,
      "tested": null,
      "toolchain": "leanprover/lean4:v4.15.0",
      "requiredUpdate": false,
      "archiveSize": 1287159,
      "archiveHash": null,
      "runAt": "2025-01-21T14:14:57Z",
      "url": "https://github.com/leanprover/reservoir/actions/runs/12888649800/job/35934247456#step:4:1",
      "revision": "767bab3af97cff1e0c2a5f2167faa67723886625"
    },
    {
      "built": true,
      "tested": null,
      "toolchain": "leanprover/lean4:v4.16.0-rc2",
      "requiredUpdate": false,
      "archiveSize": 1288394,
      "archiveHash": null,
      "runAt": "2025-01-20T14:15:30Z",
      "url": "https://github.com/leanprover/reservoir/actions/runs/12869692344/job/35879256497#step:4:1",
      "revision": "767bab3af97cff1e0c2a5f2167faa67723886625"
    },
    {
      "built": true,
      "tested": null,
      "toolchain": "leanprover/lean4:v4.13.0-rc3",
      "requiredUpdate": false,
      "archiveSize": 1295916,
      "archiveHash": null,
      "runAt": "2025-01-15T14:16:02Z",
      "url": "https://github.com/leanprover/reservoir/actions/runs/12789967057/job/35654858473#step:4:1",
      "revision": "c2d5c038f9faadda744d7e6d28a46ff417ca1e32"
    },
    {
      "built": false,
      "tested": null,
      "toolchain": "leanprover/lean4:v4.16.0-rc1",
      "requiredUpdate": false,
      "archiveSize": null,
      "archiveHash": null,
      "runAt": "2025-01-12T14:33:03Z",
      "url": "https://github.com/leanprover/reservoir/actions/runs/12734190873/job/35491511137#step:4:1",
      "revision": "c2d5c038f9faadda744d7e6d28a46ff417ca1e32"
    },
    {
      "built": false,
      "tested": null,
      "toolchain": "leanprover/lean4:v4.15.0",
      "requiredUpdate": false,
      "archiveSize": null,
      "archiveHash": null,
      "runAt": "2025-01-11T14:35:09Z",
      "url": "https://github.com/leanprover/reservoir/actions/runs/12724862398/job/35471537479#step:4:1",
      "revision": "c2d5c038f9faadda744d7e6d28a46ff417ca1e32"
    },
    {
      "built": false,
      "tested": null,
      "toolchain": "leanprover/lean4:v4.15.0-rc1",
      "requiredUpdate": false,
      "archiveSize": null,
      "archiveHash": null,
      "runAt": "2025-01-02T14:08:50Z",
      "url": "https://github.com/leanprover/reservoir/actions/runs/12583600161/job/35071615454#step:4:1",
      "revision": "c2d5c038f9faadda744d7e6d28a46ff417ca1e32"
    }
  ]
}
