{
  "name": "synthetic_euclid_4",
  "owner": "ah1112",
  "fullName": "ah1112/synthetic_euclid_4",
  "description": null,
  "homepage": null,
  "license": "Apache-2.0",
  "createdAt": "2023-04-05T20:24:12Z",
  "updatedAt": "2023-12-20T19:09:58Z",
  "stars": 8,
  "sources": [
    {
      "type": "git",
      "host": "github",
      "id": "R_kgDOJTOL_g",
      "fullName": "ah1112/synthetic_euclid_4",
      "repoUrl": "https://github.com/ah1112/synthetic_euclid_4",
      "gitUrl": "https://github.com/ah1112/synthetic_euclid_4",
      "defaultBranch": "main"
    }
  ]
}
