{
  "name": "vizagrams",
  "owner": "arademaker",
  "fullName": "arademaker/vizagrams",
  "description": "A visualization library for Lean",
  "keywords": [],
  "homepage": null,
  "license": "Apache-2.0",
  "createdAt": "2024-10-11T15:13:10Z",
  "updatedAt": "2026-04-08T17:12:34Z",
  "stars": 5,
  "sources": [
    {
      "type": "git",
      "host": "github",
      "id": "R_kgDOM-5EKw",
      "fullName": "arademaker/vizagrams",
      "repoUrl": "https://github.com/arademaker/vizagrams",
      "gitUrl": "https://github.com/arademaker/vizagrams",
      "defaultBranch": "main"
    }
  ],
  "schemaVersion": "1.2.0"
}
