{
  "schemaVersion": "1.0.0",
  "data": [
    {
      "built": false,
      "tested": null,
      "toolchain": "leanprover/lean4:v4.8.0",
      "requiredUpdate": false,
      "archiveSize": null,
      "runAt": "2024-09-17T16:48:39Z",
      "url": "https://github.com/leanprover/reservoir/actions/runs/10907439769/job/30271241645#step:4:1",
      "revision": "1a0e13606be5a21145723d17490589a2c617b6f9"
    },
    {
      "built": false,
      "tested": null,
      "toolchain": "leanprover/lean4:v4.8.0",
      "requiredUpdate": false,
      "archiveSize": null,
      "runAt": "2024-09-15T22:16:53Z",
      "url": "https://github.com/leanprover/reservoir/actions/runs/10874708944/job/30172328157#step:4:1",
      "revision": "1a0e13606be5a21145723d17490589a2c617b6f9"
    },
    {
      "built": false,
      "tested": null,
      "toolchain": "leanprover/lean4:v4.12.0-rc1",
      "requiredUpdate": null,
      "archiveSize": null,
      "runAt": "2024-09-15T14:24:51Z",
      "url": "https://github.com/leanprover/reservoir/actions/runs/10871643743/job/30165777687#step:4:1",
      "revision": "1a0e13606be5a21145723d17490589a2c617b6f9"
    },
    {
      "built": false,
      "tested": null,
      "toolchain": "leanprover/lean4:v4.11.0",
      "requiredUpdate": null,
      "archiveSize": null,
      "runAt": "2024-09-14T17:12:32Z",
      "url": "https://github.com/leanprover/reservoir/actions/runs/10863019024/job/30146740360#step:4:1",
      "revision": "1a0e13606be5a21145723d17490589a2c617b6f9"
    },
    {
      "built": false,
      "tested": null,
      "toolchain": "leanprover/lean4:v4.11.0-rc3",
      "requiredUpdate": null,
      "archiveSize": null,
      "runAt": "2024-09-01T14:22:45Z",
      "url": "https://github.com/leanprover/reservoir/actions/runs/10654668023/job/29531325486#step:4:1",
      "revision": "1a0e13606be5a21145723d17490589a2c617b6f9"
    },
    {
      "built": false,
      "tested": null,
      "toolchain": "leanprover/lean4:v4.10.0",
      "requiredUpdate": null,
      "archiveSize": null,
      "runAt": "2024-08-31T16:48:15Z",
      "url": "https://github.com/leanprover/reservoir/actions/runs/10645855657/job/29512124823#step:4:1",
      "revision": "1a0e13606be5a21145723d17490589a2c617b6f9"
    },
    {
      "built": false,
      "tested": null,
      "toolchain": "leanprover/lean4:v4.11.0-rc2",
      "requiredUpdate": null,
      "archiveSize": null,
      "runAt": "2024-08-25T14:22:13Z",
      "url": "https://github.com/leanprover/reservoir/actions/runs/10547565248/job/29220469355#step:4:1",
      "revision": "1a0e13606be5a21145723d17490589a2c617b6f9"
    },
    {
      "built": false,
      "tested": null,
      "toolchain": "leanprover/lean4:v4.11.0-rc1",
      "requiredUpdate": null,
      "archiveSize": null,
      "runAt": "2024-08-11T15:15:51Z",
      "url": "https://github.com/leanprover/reservoir/actions/runs/10340342131/job/28620904876#step:4:1",
      "revision": "1a0e13606be5a21145723d17490589a2c617b6f9"
    },
    {
      "built": false,
      "tested": null,
      "toolchain": "leanprover/lean4:v4.8.0",
      "requiredUpdate": null,
      "archiveSize": null,
      "runAt": "2024-08-05T14:37:16Z",
      "url": "https://github.com/leanprover/reservoir/actions/runs/10250296539/job/28355875666#step:4:1",
      "revision": "1a0e13606be5a21145723d17490589a2c617b6f9"
    },
    {
      "built": false,
      "tested": null,
      "toolchain": "leanprover/lean4:v4.9.1",
      "requiredUpdate": null,
      "archiveSize": null,
      "runAt": "2024-07-30T16:52:54Z",
      "url": "https://github.com/leanprover/reservoir/actions/runs/10163897541/job/28108173819#step:4:1",
      "revision": "1a0e13606be5a21145723d17490589a2c617b6f9"
    },
    {
      "built": false,
      "tested": null,
      "toolchain": "leanprover/lean4:v4.10.0-rc2",
      "requiredUpdate": null,
      "archiveSize": null,
      "runAt": "2024-07-28T16:42:33Z",
      "url": "https://github.com/leanprover/reservoir/actions/runs/10132302513/job/28016175052#step:4:1",
      "revision": "1a0e13606be5a21145723d17490589a2c617b6f9"
    },
    {
      "built": false,
      "tested": null,
      "toolchain": "leanprover/lean4:v4.9.0",
      "requiredUpdate": null,
      "archiveSize": null,
      "runAt": "2024-07-09T16:47:21Z",
      "url": "https://github.com/leanprover/reservoir/actions/runs/9858485245/job/27220161677#step:4:1",
      "revision": "1a0e13606be5a21145723d17490589a2c617b6f9"
    },
    {
      "url": "https://github.com/leanprover/reservoir/actions/runs/9695058833/job/26754117491#step:4:1",
      "built": false,
      "tested": null,
      "archiveSize": null,
      "toolchain": "leanprover/lean4:v4.9.0-rc3",
      "requiredUpdate": null,
      "revision": "723ea89a38ed213d7be696e15ccf1bd4b35e6af9",
      "runAt": "2024-06-27T13:20:01Z"
    },
    {
      "url": "https://github.com/leanprover/reservoir/actions/runs/9643857493/job/26594816243#step:4:1",
      "built": false,
      "tested": null,
      "archiveSize": null,
      "toolchain": "leanprover/lean4:v4.8.0-rc1",
      "requiredUpdate": null,
      "revision": "723ea89a38ed213d7be696e15ccf1bd4b35e6af9",
      "runAt": "2024-06-24T10:52:28Z"
    },
    {
      "url": "https://github.com/leanprover/reservoir/actions/runs/9632789766/job/26566433427#step:4:1",
      "built": false,
      "tested": null,
      "archiveSize": null,
      "toolchain": "leanprover/lean4:v4.9.0-rc2",
      "requiredUpdate": null,
      "revision": "723ea89a38ed213d7be696e15ccf1bd4b35e6af9",
      "runAt": "2024-06-23T13:20:37Z"
    },
    {
      "url": "https://github.com/leanprover/reservoir/actions/runs/9498113229/job/26176254795#step:4:1",
      "built": false,
      "tested": null,
      "archiveSize": null,
      "toolchain": "leanprover/lean4:v4.9.0-rc1",
      "requiredUpdate": null,
      "revision": "a716dec2041f72be79db9529c656c2741809578b",
      "runAt": "2024-06-13T10:51:10Z"
    },
    {
      "url": "https://github.com/leanprover/reservoir/actions/runs/9337613247/job/25699737793#step:4:1",
      "built": false,
      "tested": null,
      "archiveSize": null,
      "toolchain": "leanprover/lean4:v4.8.0-rc2",
      "requiredUpdate": null,
      "revision": "15501d24d6001bac22bcffa584dcf5b4c15755f7",
      "runAt": "2024-06-02T13:18:07Z"
    },
    {
      "url": "https://github.com/leanprover/reservoir/actions/runs/8983854810/job/24674584126#step:4:1",
      "built": true,
      "tested": null,
      "archiveSize": null,
      "toolchain": "leanprover/lean4:v4.7.0",
      "requiredUpdate": null,
      "revision": "a6972eb55a44cbcb7bdb3cc38a460073eb8ca428",
      "runAt": "2024-05-07T11:43:05Z"
    },
    {
      "url": "https://github.com/leanprover/reservoir/actions/runs/8967728276/job/24625863157#step:4:1",
      "built": true,
      "tested": null,
      "archiveSize": null,
      "toolchain": "leanprover/lean4:v4.2.0",
      "requiredUpdate": null,
      "revision": "a6972eb55a44cbcb7bdb3cc38a460073eb8ca428",
      "runAt": "2024-05-06T10:51:22Z"
    },
    {
      "url": "https://github.com/leanprover/reservoir/actions/runs/8434573492/job/23098146774#step:4:1",
      "built": true,
      "tested": null,
      "archiveSize": null,
      "toolchain": "leanprover/lean4:v4.6.1",
      "requiredUpdate": null,
      "revision": "a6972eb55a44cbcb7bdb3cc38a460073eb8ca428",
      "runAt": "2024-03-26T11:53:04Z"
    },
    {
      "url": "https://github.com/leanprover/reservoir/actions/runs/8408704594/job/23025188700#step:4:1",
      "built": true,
      "tested": null,
      "archiveSize": null,
      "toolchain": "leanprover/lean4:v4.7.0-rc2",
      "requiredUpdate": null,
      "revision": "a6972eb55a44cbcb7bdb3cc38a460073eb8ca428",
      "runAt": "2024-03-24T10:51:41Z"
    },
    {
      "url": "https://github.com/leanprover/reservoir/actions/runs/8129593362/job/22216878709#step:4:1",
      "built": true,
      "tested": null,
      "archiveSize": null,
      "toolchain": "leanprover/lean4:v4.6.0",
      "requiredUpdate": null,
      "revision": "a6972eb55a44cbcb7bdb3cc38a460073eb8ca428",
      "runAt": "2024-03-03T11:51:43Z"
    },
    {
      "url": "https://github.com/leanprover/reservoir/actions/runs/8037357239/job/21952112079#step:4:1",
      "built": true,
      "tested": null,
      "archiveSize": null,
      "toolchain": "leanprover/lean4:v4.6.0-rc1",
      "requiredUpdate": null,
      "revision": "a6972eb55a44cbcb7bdb3cc38a460073eb8ca428",
      "runAt": "2024-02-25T11:01:02Z"
    },
    {
      "url": "https://github.com/leanprover/reservoir/actions/runs/8029984520/job/21936882092#step:4:1",
      "built": true,
      "tested": null,
      "archiveSize": null,
      "toolchain": "leanprover/lean4:v4.5.0",
      "requiredUpdate": null,
      "revision": "a6972eb55a44cbcb7bdb3cc38a460073eb8ca428",
      "runAt": "2024-02-24T13:22:42Z"
    },
    {
      "url": "https://github.com/leanprover/reservoir/actions/runs/7709826154/job/21011880869#step:4:1",
      "built": true,
      "tested": null,
      "archiveSize": null,
      "toolchain": "leanprover/lean4:v4.4.0",
      "requiredUpdate": null,
      "revision": "a6972eb55a44cbcb7bdb3cc38a460073eb8ca428",
      "runAt": "2024-01-30T13:31:30Z"
    },
    {
      "url": "https://github.com/leanprover/reservoir/actions/runs/7685162967/job/20942525848#step:4:1",
      "built": true,
      "tested": null,
      "archiveSize": null,
      "toolchain": "leanprover/lean4:v4.5.0-rc1",
      "requiredUpdate": null,
      "revision": "a6972eb55a44cbcb7bdb3cc38a460073eb8ca428",
      "runAt": "2024-01-28T11:03:01Z"
    },
    {
      "url": "https://github.com/leanprover/reservoir/actions/runs/7274203214/job/19819687009#step:4:1",
      "built": true,
      "tested": null,
      "archiveSize": null,
      "toolchain": "leanprover/lean4:v4.4.0-rc1",
      "requiredUpdate": null,
      "revision": "a6972eb55a44cbcb7bdb3cc38a460073eb8ca428",
      "runAt": "2023-12-20T11:16:53Z"
    }
  ]
}
