{
  "schemaVersion": "1.2.0",
  "data": [
    {
      "built": false,
      "tested": null,
      "toolchain": "leanprover/lean4:v4.21.0",
      "requiredUpdate": false,
      "archiveSize": null,
      "archiveHash": null,
      "runAt": "2025-07-12T14:07:04Z",
      "url": "https://github.com/leanprover/reservoir/actions/runs/16238763073/job/45852374220#step:4:1",
      "revision": "9d1f1a6726fcc90dac608bc582be9e841a42ee3d"
    },
    {
      "built": true,
      "tested": null,
      "toolchain": "leanprover/lean4:v4.19.0-rc3",
      "requiredUpdate": false,
      "archiveSize": 1051149,
      "archiveHash": null,
      "runAt": "2025-07-11T14:04:15Z",
      "url": "https://github.com/leanprover/reservoir/actions/runs/16221917558/job/45804421972#step:4:1",
      "revision": "9d1f1a6726fcc90dac608bc582be9e841a42ee3d"
    },
    {
      "built": false,
      "tested": null,
      "toolchain": "leanprover/lean4:v4.22.0-rc3",
      "requiredUpdate": false,
      "archiveSize": null,
      "archiveHash": null,
      "runAt": "2025-07-10T14:08:06Z",
      "url": "https://github.com/leanprover/reservoir/actions/runs/16197286615/job/45727106317#step:4:1",
      "revision": "9d1f1a6726fcc90dac608bc582be9e841a42ee3d"
    },
    {
      "built": true,
      "tested": null,
      "toolchain": "leanprover/lean4:v4.19.0-rc3",
      "requiredUpdate": false,
      "archiveSize": 1051151,
      "archiveHash": null,
      "runAt": "2025-07-09T14:06:13Z",
      "url": "https://github.com/leanprover/reservoir/actions/runs/16171453323/job/45645896459#step:4:1",
      "revision": "9d1f1a6726fcc90dac608bc582be9e841a42ee3d"
    },
    {
      "built": false,
      "tested": null,
      "toolchain": "leanprover/lean4:v4.21.0",
      "requiredUpdate": false,
      "archiveSize": null,
      "archiveHash": null,
      "runAt": "2025-07-08T14:09:16Z",
      "url": "https://github.com/leanprover/reservoir/actions/runs/16145525043/job/45563345723#step:4:1",
      "revision": "9d1f1a6726fcc90dac608bc582be9e841a42ee3d"
    },
    {
      "built": true,
      "tested": null,
      "toolchain": "leanprover/lean4:v4.19.0-rc3",
      "requiredUpdate": false,
      "archiveSize": 1051147,
      "archiveHash": null,
      "runAt": "2025-07-07T14:04:31Z",
      "url": "https://github.com/leanprover/reservoir/actions/runs/16119109422/job/45480162464#step:4:1",
      "revision": "9d1f1a6726fcc90dac608bc582be9e841a42ee3d"
    },
    {
      "built": false,
      "tested": null,
      "toolchain": "leanprover/lean4:v4.22.0-rc3",
      "requiredUpdate": false,
      "archiveSize": null,
      "archiveHash": null,
      "runAt": "2025-07-06T14:06:45Z",
      "url": "https://github.com/leanprover/reservoir/actions/runs/16099811350/job/45427513367#step:4:1",
      "revision": "9d1f1a6726fcc90dac608bc582be9e841a42ee3d"
    },
    {
      "built": false,
      "tested": null,
      "toolchain": "leanprover/lean4:v4.21.0",
      "requiredUpdate": false,
      "archiveSize": null,
      "archiveHash": null,
      "runAt": "2025-07-05T14:07:35Z",
      "url": "https://github.com/leanprover/reservoir/actions/runs/16088861509/job/45403343058#step:4:1",
      "revision": "9d1f1a6726fcc90dac608bc582be9e841a42ee3d"
    },
    {
      "built": true,
      "tested": null,
      "toolchain": "leanprover/lean4:v4.19.0-rc3",
      "requiredUpdate": false,
      "archiveSize": 1051150,
      "archiveHash": null,
      "runAt": "2025-07-04T14:06:07Z",
      "url": "https://github.com/leanprover/reservoir/actions/runs/16075482095/job/45369677159#step:4:1",
      "revision": "9d1f1a6726fcc90dac608bc582be9e841a42ee3d"
    },
    {
      "built": false,
      "tested": null,
      "toolchain": "leanprover/lean4:v4.22.0-rc2",
      "requiredUpdate": false,
      "archiveSize": null,
      "archiveHash": null,
      "runAt": "2025-07-03T14:05:11Z",
      "url": "https://github.com/leanprover/reservoir/actions/runs/16052563016/job/45298806075#step:4:1",
      "revision": "9d1f1a6726fcc90dac608bc582be9e841a42ee3d"
    },
    {
      "built": true,
      "tested": null,
      "toolchain": "leanprover/lean4:v4.19.0-rc3",
      "requiredUpdate": false,
      "archiveSize": 1051134,
      "archiveHash": null,
      "runAt": "2025-07-02T14:06:39Z",
      "url": "https://github.com/leanprover/reservoir/actions/runs/16027255991/job/45218402852#step:4:1",
      "revision": "9d1f1a6726fcc90dac608bc582be9e841a42ee3d"
    },
    {
      "built": false,
      "tested": null,
      "toolchain": "leanprover/lean4:v4.21.0",
      "requiredUpdate": false,
      "archiveSize": null,
      "archiveHash": null,
      "runAt": "2025-07-01T14:06:41Z",
      "url": "https://github.com/leanprover/reservoir/actions/runs/16001620169/job/45137923354#step:4:1",
      "revision": "9d1f1a6726fcc90dac608bc582be9e841a42ee3d"
    },
    {
      "built": true,
      "tested": null,
      "toolchain": "leanprover/lean4:v4.19.0-rc3",
      "requiredUpdate": false,
      "archiveSize": 1051162,
      "archiveHash": null,
      "runAt": "2025-06-30T14:05:23Z",
      "url": "https://github.com/leanprover/reservoir/actions/runs/15975051308/job/45055342467#step:4:1",
      "revision": "9d1f1a6726fcc90dac608bc582be9e841a42ee3d"
    },
    {
      "built": false,
      "tested": null,
      "toolchain": "leanprover/lean4:v4.21.0-rc3",
      "requiredUpdate": false,
      "archiveSize": null,
      "archiveHash": null,
      "runAt": "2025-06-29T14:06:24Z",
      "url": "https://github.com/leanprover/reservoir/actions/runs/15955993748/job/45002382973#step:4:1",
      "revision": "9d1f1a6726fcc90dac608bc582be9e841a42ee3d"
    },
    {
      "built": false,
      "tested": null,
      "toolchain": "leanprover/lean4:v4.20.1",
      "requiredUpdate": false,
      "archiveSize": null,
      "archiveHash": null,
      "runAt": "2025-06-28T14:08:07Z",
      "url": "https://github.com/leanprover/reservoir/actions/runs/15944905406/job/44977754232#step:4:1",
      "revision": "9d1f1a6726fcc90dac608bc582be9e841a42ee3d"
    },
    {
      "built": true,
      "tested": null,
      "toolchain": "leanprover/lean4:v4.19.0-rc3",
      "requiredUpdate": false,
      "archiveSize": 1051158,
      "archiveHash": null,
      "runAt": "2025-06-27T14:03:09Z",
      "url": "https://github.com/leanprover/reservoir/actions/runs/15928151255/job/44930468500#step:4:1",
      "revision": "9d1f1a6726fcc90dac608bc582be9e841a42ee3d"
    },
    {
      "built": false,
      "tested": null,
      "toolchain": "leanprover/lean4:v4.21.0-rc3",
      "requiredUpdate": false,
      "archiveSize": null,
      "archiveHash": null,
      "runAt": "2025-06-26T14:06:34Z",
      "url": "https://github.com/leanprover/reservoir/actions/runs/15904000110/job/44853978864#step:4:1",
      "revision": "9d1f1a6726fcc90dac608bc582be9e841a42ee3d"
    },
    {
      "built": true,
      "tested": null,
      "toolchain": "leanprover/lean4:v4.19.0-rc3",
      "requiredUpdate": false,
      "archiveSize": 1051827,
      "archiveHash": null,
      "runAt": "2025-06-25T14:05:31Z",
      "url": "https://github.com/leanprover/reservoir/actions/runs/15878499508/job/44772277397#step:4:1",
      "revision": "9d1f1a6726fcc90dac608bc582be9e841a42ee3d"
    },
    {
      "built": false,
      "tested": null,
      "toolchain": "leanprover/lean4:v4.20.1",
      "requiredUpdate": false,
      "archiveSize": null,
      "archiveHash": null,
      "runAt": "2025-06-24T14:09:21Z",
      "url": "https://github.com/leanprover/reservoir/actions/runs/15852688772/job/44690142881#step:4:1",
      "revision": "9d1f1a6726fcc90dac608bc582be9e841a42ee3d"
    },
    {
      "built": true,
      "tested": null,
      "toolchain": "leanprover/lean4:v4.19.0-rc3",
      "requiredUpdate": false,
      "archiveSize": 1051820,
      "archiveHash": null,
      "runAt": "2025-06-23T14:05:34Z",
      "url": "https://github.com/leanprover/reservoir/actions/runs/15826385555/job/44607677489#step:4:1",
      "revision": "9d1f1a6726fcc90dac608bc582be9e841a42ee3d"
    },
    {
      "built": false,
      "tested": null,
      "toolchain": "leanprover/lean4:v4.21.0-rc3",
      "requiredUpdate": false,
      "archiveSize": null,
      "archiveHash": null,
      "runAt": "2025-06-22T14:06:19Z",
      "url": "https://github.com/leanprover/reservoir/actions/runs/15807378794/job/44554097728#step:4:1",
      "revision": "9d1f1a6726fcc90dac608bc582be9e841a42ee3d"
    },
    {
      "built": false,
      "tested": null,
      "toolchain": "leanprover/lean4:v4.20.1",
      "requiredUpdate": false,
      "archiveSize": null,
      "archiveHash": null,
      "runAt": "2025-06-21T14:06:38Z",
      "url": "https://github.com/leanprover/reservoir/actions/runs/15796452405/job/44529129049#step:4:1",
      "revision": "9d1f1a6726fcc90dac608bc582be9e841a42ee3d"
    },
    {
      "built": false,
      "tested": null,
      "toolchain": "leanprover/lean4:v4.19.0-rc3",
      "requiredUpdate": false,
      "archiveSize": null,
      "archiveHash": null,
      "runAt": "2025-06-20T14:09:39Z",
      "url": "https://github.com/leanprover/reservoir/actions/runs/15780677939/job/44485386192#step:4:1",
      "revision": "2c93e385bb546aaab8ac5f502d2984b92473eda4"
    },
    {
      "built": false,
      "tested": null,
      "toolchain": "leanprover/lean4:v4.21.0-rc3",
      "requiredUpdate": false,
      "archiveSize": null,
      "archiveHash": null,
      "runAt": "2025-06-19T14:07:51Z",
      "url": "https://github.com/leanprover/reservoir/actions/runs/15759742725/job/44423420264#step:4:1",
      "revision": "2c93e385bb546aaab8ac5f502d2984b92473eda4"
    },
    {
      "built": false,
      "tested": null,
      "toolchain": "leanprover/lean4:v4.20.1",
      "requiredUpdate": false,
      "archiveSize": null,
      "archiveHash": null,
      "runAt": "2025-06-17T14:09:15Z",
      "url": "https://github.com/leanprover/reservoir/actions/runs/15709493990/job/44263650946#step:4:1",
      "revision": "2c93e385bb546aaab8ac5f502d2984b92473eda4"
    },
    {
      "built": false,
      "tested": null,
      "toolchain": "leanprover/lean4:v4.20.1",
      "requiredUpdate": false,
      "archiveSize": null,
      "archiveHash": null,
      "runAt": "2025-06-07T14:16:46Z",
      "url": "https://github.com/leanprover/reservoir/actions/runs/15508553665/job/43666517291#step:4:1",
      "revision": "814ba0f6385e96eaa5d45bb3cee2362798a17488"
    },
    {
      "built": false,
      "tested": null,
      "toolchain": "leanprover/lean4:v4.19.0-rc3",
      "requiredUpdate": false,
      "archiveSize": null,
      "archiveHash": null,
      "runAt": "2025-06-06T14:06:22Z",
      "url": "https://github.com/leanprover/reservoir/actions/runs/15492360492/job/43620970978#step:4:1",
      "revision": "814ba0f6385e96eaa5d45bb3cee2362798a17488"
    },
    {
      "built": false,
      "tested": null,
      "toolchain": "leanprover/lean4:v4.20.0",
      "requiredUpdate": false,
      "archiveSize": null,
      "archiveHash": null,
      "runAt": "2025-06-03T14:10:13Z",
      "url": "https://github.com/leanprover/reservoir/actions/runs/15419527448/job/43390755118#step:4:1",
      "revision": "814ba0f6385e96eaa5d45bb3cee2362798a17488"
    },
    {
      "built": false,
      "tested": null,
      "toolchain": "leanprover/lean4:v4.20.0-rc5",
      "requiredUpdate": false,
      "archiveSize": null,
      "archiveHash": null,
      "runAt": "2025-06-01T14:06:20Z",
      "url": "https://github.com/leanprover/reservoir/actions/runs/15375900211/job/43260650913#step:4:1",
      "revision": "814ba0f6385e96eaa5d45bb3cee2362798a17488"
    },
    {
      "built": false,
      "tested": null,
      "toolchain": "leanprover/lean4:v4.19.0",
      "requiredUpdate": false,
      "archiveSize": null,
      "archiveHash": null,
      "runAt": "2025-05-31T14:17:32Z",
      "url": "https://github.com/leanprover/reservoir/actions/runs/15364391185/job/43235508558#step:4:1",
      "revision": "814ba0f6385e96eaa5d45bb3cee2362798a17488"
    },
    {
      "built": false,
      "tested": null,
      "toolchain": "leanprover/lean4:v4.19.0-rc3",
      "requiredUpdate": false,
      "archiveSize": null,
      "archiveHash": null,
      "runAt": "2025-05-28T14:21:51Z",
      "url": "https://github.com/leanprover/reservoir/actions/runs/15302185623/job/43045822668#step:4:1",
      "revision": "cd25458575012e4bd92a34b6d13234015c8d62a5"
    },
    {
      "built": false,
      "tested": null,
      "toolchain": "leanprover/lean4:v4.19.0",
      "requiredUpdate": false,
      "archiveSize": null,
      "archiveHash": null,
      "runAt": "2025-05-27T14:18:11Z",
      "url": "https://github.com/leanprover/reservoir/actions/runs/15277435034/job/42967759105#step:4:1",
      "revision": "cd25458575012e4bd92a34b6d13234015c8d62a5"
    },
    {
      "built": false,
      "tested": null,
      "toolchain": "leanprover/lean4:v4.20.0-rc5",
      "requiredUpdate": false,
      "archiveSize": null,
      "archiveHash": null,
      "runAt": "2025-05-25T14:19:36Z",
      "url": "https://github.com/leanprover/reservoir/actions/runs/15238650490/job/42855968595#step:4:1",
      "revision": "5457a4c199052d69da7059e1af6d8c6fa3c8a543"
    },
    {
      "built": false,
      "tested": null,
      "toolchain": "leanprover/lean4:v4.19.0",
      "requiredUpdate": false,
      "archiveSize": null,
      "archiveHash": null,
      "runAt": "2025-05-24T14:16:54Z",
      "url": "https://github.com/leanprover/reservoir/actions/runs/15227795161/job/42832034389#step:4:1",
      "revision": "5457a4c199052d69da7059e1af6d8c6fa3c8a543"
    },
    {
      "built": false,
      "tested": null,
      "toolchain": "leanprover/lean4:v4.19.0-rc3",
      "requiredUpdate": false,
      "archiveSize": null,
      "archiveHash": null,
      "runAt": "2025-05-23T14:21:03Z",
      "url": "https://github.com/leanprover/reservoir/actions/runs/15212115422/job/42788862640#step:4:1",
      "revision": "5457a4c199052d69da7059e1af6d8c6fa3c8a543"
    },
    {
      "built": false,
      "tested": null,
      "toolchain": "leanprover/lean4:v4.20.0-rc5",
      "requiredUpdate": false,
      "archiveSize": null,
      "archiveHash": null,
      "runAt": "2025-05-22T14:15:45Z",
      "url": "https://github.com/leanprover/reservoir/actions/runs/15188677921/job/42715847077#step:4:1",
      "revision": "5394ff3cd9c7e498a03802e8acd1780f143492b1"
    },
    {
      "built": true,
      "tested": null,
      "toolchain": "leanprover/lean4:v4.19.0-rc3",
      "requiredUpdate": false,
      "archiveSize": 355411,
      "archiveHash": null,
      "runAt": "2025-05-19T14:07:55Z",
      "url": "https://github.com/leanprover/reservoir/actions/runs/15115047030/job/42483712321#step:4:1",
      "revision": "a5f222a934d57e63e2edd7b0f6eec48307403991"
    }
  ]
}
