{
  "name": "OSforGFF",
  "owner": "mrdouglasny",
  "fullName": "mrdouglasny/OSforGFF",
  "description": "A Lean 4 formalization of the Gaussian Free Field in d=4 and proof of the Osterwalder-Schrader axioms",
  "keywords": [],
  "homepage": null,
  "license": "Apache-2.0",
  "createdAt": "2026-02-08T21:33:22Z",
  "updatedAt": "2026-02-28T17:32:26Z",
  "stars": 8,
  "sources": [
    {
      "type": "git",
      "host": "github",
      "id": "R_kgDORLqW6w",
      "fullName": "mrdouglasny/OSforGFF",
      "repoUrl": "https://github.com/mrdouglasny/OSforGFF",
      "gitUrl": "https://github.com/mrdouglasny/OSforGFF",
      "defaultBranch": "main"
    }
  ],
  "schemaVersion": "1.2.0"
}
