{
  "name": "cryptolib",
  "owner": "atrieu",
  "fullName": "atrieu/cryptolib",
  "description": null,
  "keywords": [
    "math"
  ],
  "homepage": null,
  "license": "Apache-2.0",
  "createdAt": "2025-03-28T14:08:35Z",
  "updatedAt": "2025-04-29T15:57:22Z",
  "stars": 3,
  "sources": [
    {
      "type": "git",
      "host": "github",
      "id": "R_kgDOOQRj1A",
      "fullName": "atrieu/lean-cryptolib",
      "repoUrl": "https://github.com/atrieu/lean-cryptolib",
      "gitUrl": "https://github.com/atrieu/lean-cryptolib",
      "defaultBranch": "main"
    }
  ],
  "schemaVersion": "1.2.0"
}
