{
  "name": "graphiti",
  "owner": "VCA-EPFL",
  "fullName": "VCA-EPFL/graphiti",
  "description": "Verified graph rewriting (for dataflow circuits).",
  "keywords": [],
  "homepage": null,
  "license": "Apache-2.0",
  "createdAt": "2024-06-24T10:10:56Z",
  "updatedAt": "2025-11-15T18:35:41Z",
  "stars": 17,
  "sources": [
    {
      "type": "git",
      "host": "github",
      "id": "R_kgDOMNYu8A",
      "fullName": "VCA-EPFL/graphiti",
      "repoUrl": "https://github.com/VCA-EPFL/graphiti",
      "gitUrl": "https://github.com/VCA-EPFL/graphiti",
      "defaultBranch": "main"
    }
  ],
  "schemaVersion": "1.2.0"
}
