{
  "name": "Wasm.lean",
  "owner": "argumentcomputer",
  "fullName": "argumentcomputer/Wasm.lean",
  "description": "A WebAssembly implementation in Lean4",
  "homepage": null,
  "license": "MIT",
  "createdAt": "2022-03-31T10:49:40Z",
  "updatedAt": "2024-08-20T15:04:59Z",
  "stars": 29,
  "sources": [
    {
      "type": "git",
      "host": "github",
      "id": "R_kgDOHGM0Ag",
      "fullName": "argumentcomputer/Wasm.lean",
      "repoUrl": "https://github.com/argumentcomputer/Wasm.lean",
      "gitUrl": "https://github.com/argumentcomputer/Wasm.lean",
      "defaultBranch": "main"
    }
  ]
}
