{
  "schemaVersion": "1.2.0",
  "data": [
    {
      "built": true,
      "tested": null,
      "toolchain": "leanprover/lean4:v4.16.0-rc2",
      "requiredUpdate": false,
      "archiveSize": 19282063,
      "archiveHash": null,
      "runAt": "2025-02-12T14:19:08Z",
      "url": "https://github.com/leanprover/reservoir/actions/runs/13287148260/job/37098681165#step:4:1",
      "revision": "54fdc60c522e6222d7d0b9755f944bdac04419d8"
    },
    {
      "built": true,
      "tested": null,
      "toolchain": "leanprover/lean4:v4.17.0-rc1",
      "requiredUpdate": false,
      "archiveSize": 18983019,
      "archiveHash": null,
      "runAt": "2025-02-09T14:12:40Z",
      "url": "https://github.com/leanprover/reservoir/actions/runs/13226419003/job/36917909805#step:4:1",
      "revision": "76bc70fed5ece8375d504346e79ede2ab44cb40b"
    },
    {
      "built": true,
      "tested": null,
      "toolchain": "leanprover/lean4:v4.16.0",
      "requiredUpdate": false,
      "archiveSize": 18983380,
      "archiveHash": null,
      "runAt": "2025-02-08T14:14:27Z",
      "url": "https://github.com/leanprover/reservoir/actions/runs/13216331473/job/36896080826#step:4:1",
      "revision": "f32a9c51b737fa57d0b2053bedb360f37109cbe0"
    },
    {
      "built": true,
      "tested": null,
      "toolchain": "leanprover/lean4:v4.17.0-rc1",
      "requiredUpdate": false,
      "archiveSize": 18983398,
      "archiveHash": null,
      "runAt": "2025-02-06T14:14:04Z",
      "url": "https://github.com/leanprover/reservoir/actions/runs/13180511845/job/36790118650#step:4:1",
      "revision": "f32a9c51b737fa57d0b2053bedb360f37109cbe0"
    },
    {
      "built": true,
      "tested": null,
      "toolchain": "leanprover/lean4:v4.16.0-rc2",
      "requiredUpdate": false,
      "archiveSize": 18976845,
      "archiveHash": null,
      "runAt": "2025-02-05T14:17:35Z",
      "url": "https://github.com/leanprover/reservoir/actions/runs/13159093594/job/36723296123#step:4:1",
      "revision": "f32a9c51b737fa57d0b2053bedb360f37109cbe0"
    },
    {
      "built": true,
      "tested": null,
      "toolchain": "leanprover/lean4:v4.15.0",
      "requiredUpdate": false,
      "archiveSize": 18980215,
      "archiveHash": null,
      "runAt": "2025-02-01T14:15:07Z",
      "url": "https://github.com/leanprover/reservoir/actions/runs/13089329110/job/36524223250#step:4:1",
      "revision": "f32a9c51b737fa57d0b2053bedb360f37109cbe0"
    },
    {
      "built": true,
      "tested": null,
      "toolchain": "leanprover/lean4:v4.16.0-rc2",
      "requiredUpdate": false,
      "archiveSize": 19053362,
      "archiveHash": null,
      "runAt": "2025-01-23T14:13:42Z",
      "url": "https://github.com/leanprover/reservoir/actions/runs/12930848792/job/36063546817#step:4:1",
      "revision": "a90ccae04fe1bae94ab38005f71bc1a217526a18"
    },
    {
      "built": true,
      "tested": null,
      "toolchain": "leanprover/lean4:v4.15.0",
      "requiredUpdate": false,
      "archiveSize": 19254486,
      "archiveHash": null,
      "runAt": "2025-01-22T14:17:30Z",
      "url": "https://github.com/leanprover/reservoir/actions/runs/12909882023/job/35998837739#step:4:1",
      "revision": "98fce9efa804873df8548166741440af695fc707"
    },
    {
      "built": true,
      "tested": null,
      "toolchain": "leanprover/lean4:v4.15.0",
      "requiredUpdate": false,
      "archiveSize": 19153158,
      "archiveHash": null,
      "runAt": "2025-01-21T14:15:21Z",
      "url": "https://github.com/leanprover/reservoir/actions/runs/12888649800/job/35934249054#step:4:1",
      "revision": "6ffb5be9584120a3245b229895ec17c172a9859e"
    },
    {
      "built": true,
      "tested": null,
      "toolchain": "leanprover/lean4:v4.16.0-rc2",
      "requiredUpdate": false,
      "archiveSize": 19152968,
      "archiveHash": null,
      "runAt": "2025-01-19T14:12:39Z",
      "url": "https://github.com/leanprover/reservoir/actions/runs/12854234622/job/35838406615#step:4:1",
      "revision": "6ffb5be9584120a3245b229895ec17c172a9859e"
    }
  ]
}
